crawler/__init__.py
my_custom_crawler-0.1.2.dist-info/WHEEL
my_custom_crawler-0.1.2.dist-info/METADATA
my_custom_crawler-0.1.2.dist-info/RECORD
