Metadata-Version: 2.1
Name: my-custom-crawler
Version: 0.1.2
Summary: 
Author: Ignacio Vargas
Author-email: ignaciovrgs@hotmail.com
Requires-Python: >=3.10,<4.0
Classifier: Programming Language :: Python :: 3
Classifier: Programming Language :: Python :: 3.10
Classifier: Programming Language :: Python :: 3.11
Requires-Dist: twine (>=4.0.2,<5.0.0)
